Metadata-Version: 2.1
Name: certbot-dns-bonk
Version: 0.2.1
Summary: Certbot plugin for authentication using bonk
Home-page: https://github.com/dhozac/certbot-dns-bonk
Author: Daniel Hokka Zakrisson
Author-email: daniel@hozac.com
License: UNKNOWN
Platform: UNKNOWN
Classifier: Development Status :: 4 - Beta
Requires-Python: >=2.7, !=3.0.*, !=3.1.*, !=3.2.*, !=3.3.*
Requires-Dist: certbot
Requires-Dist: requests (>=2.4.2)
Requires-Dist: zope.interface
